loggerutility/__init__.py
loggerutility/deployment_logger.py
loggerutility-0.0.14.dist-info/LICENCE.txt
loggerutility-0.0.14.dist-info/METADATA
loggerutility-0.0.14.dist-info/WHEEL
loggerutility-0.0.14.dist-info/top_level.txt
loggerutility-0.0.14.dist-info/RECORD
